pyopenagi/README.md
pyopenagi/__init__.py
pyopenagi/agents/README.md
pyopenagi/agents/__init__.py
pyopenagi/agents/agent_factory.py
pyopenagi/agents/agent_process.py
pyopenagi/agents/base_agent.py
pyopenagi/agents/interact.py
pyopenagi/agents/react_agent.py
pyopenagi/agents/example/README.md
pyopenagi/agents/example/academic_agent/agent.py
pyopenagi/agents/example/academic_agent/config.json
pyopenagi/agents/example/academic_agent/meta_requirements.txt
pyopenagi/agents/example/creation_agent/agent.py
pyopenagi/agents/example/creation_agent/config.json
pyopenagi/agents/example/creation_agent/meta_requirements.txt
pyopenagi/agents/example/math_agent/agent.py
pyopenagi/agents/example/math_agent/config.json
pyopenagi/agents/example/math_agent/meta_requirements.txt
pyopenagi/agents/example/rag_agent/README.md
pyopenagi/agents/example/rag_agent/agent.py
pyopenagi/agents/example/rag_agent/config.json
pyopenagi/agents/example/rag_agent/meta_requirements.txt
pyopenagi/agents/example/rag_agent/data/paul_graham/paul_graham_essay.txt
pyopenagi/agents/example/rec_agent/agent.py
pyopenagi/agents/example/rec_agent/config.json
pyopenagi/agents/example/rec_agent/meta_requirements.txt
pyopenagi/agents/example/travel_agent/agent.py
pyopenagi/agents/example/travel_agent/config.json
pyopenagi/agents/example/travel_agent/meta_requirements.txt
pyopenagi/queues/README.md
pyopenagi/queues/base_queue.py
pyopenagi/queues/llm_request_queue.py
pyopenagi/tools/README.md
pyopenagi/tools/__init__.py
pyopenagi/tools/base.py
pyopenagi/tools/arxiv/arxiv.py
pyopenagi/tools/bing/bing_search.py
pyopenagi/tools/currency_converter/currency_converter.py
pyopenagi/tools/google/google_places.py
pyopenagi/tools/google/google_search.py
pyopenagi/tools/imdb/top_movie.py
pyopenagi/tools/imdb/top_movies.py
pyopenagi/tools/imdb/top_series.py
pyopenagi/tools/meteosource_weather/find_place.py
pyopenagi/tools/moonphase/moon_phase_search.py
pyopenagi/tools/shazam/song_auto_complete.py
agent_api-0.0.1.dist-info/METADATA
agent_api-0.0.1.dist-info/WHEEL
agent_api-0.0.1.dist-info/licenses/LICENSE
agent_api-0.0.1.dist-info/RECORD
